<?xml version="1.0" encoding="UTF-8"?>
<UnityGameFramework>
  <ResourceBuilder>
    <Settings>
      <InternalResourceVersion>39</InternalResourceVersion>
      <Platforms>2</Platforms>
      <AssetBundleCompression>1</AssetBundleCompression>
      <CompressionHelperTypeName>UnityGameFramework.Runtime.DefaultCompressionHelper</CompressionHelperTypeName>
      <AdditionalCompressionSelected>False</AdditionalCompressionSelected>
      <ForceRebuildAssetBundleSelected>False</ForceRebuildAssetBundleSelected>
      <BuildEventHandlerTypeName>BuildEventHandler</BuildEventHandlerTypeName>
      <OutputDirectory>D:/tackor/UnityProjs/Deer_GameFramework_Wolong/ResourcesFiles</OutputDirectory>
      <OutputPackageSelected>False</OutputPackageSelected>
      <OutputFullSelected>True</OutputFullSelected>
      <OutputPackedSelected>True</OutputPackedSelected>
    </Settings>
  </ResourceBuilder>
</UnityGameFramework>